{
  "version": 1,
  "base_track": "fake ring…",
  "base_artist": "429",
  "createdAt": "2026-02-25T10:16:57.655519Z",
  "candidates": [
    {
      "id": "lrclib_1",
      "source": "lrclib",
      "title": "fake ring...",
      "artist": "429",
      "has_synced": true,
      "path": "select/01_fake_ring..._429.lrc"
    },
    {
      "id": "petitlyrics_1",
      "source": "petitlyrics",
      "title": "fake ring…",
      "artist": "429",
      "has_synced": false,
      "path": "select/pl_01_fake_ring..._429.txt"
    }
  ]
}